<annotation verified="yes">
	<folder>Front_Bumper_Batch_1</folder>
	<filename>3226810.jpg</filename>
	<path>/Users/saurabhjain/INSURANCE/image-classification/ITMS_FRONT_BUMBER_DAMAGE/car_damage/Front_Bumper_Batch_1/3226810.jpg</path>
	<source>
		<database>Unknown</database>
	</source>
	<size>
		<width>1024</width>
		<height>472</height>
		<depth>3</depth>
	</size>
	<segmented>0</segmented>
	<object>
		<name>Scratched</name>
		<pose>Unspecified</pose>
		<truncated>0</truncated>
		<difficult>0</difficult>
		<bndbox>
			<xmin>541</xmin>
			<ymin>310</ymin>
			<xmax>556</xmax>
			<ymax>318</ymax>
		</bndbox>
	</object>
	<object>
		<name>Scratched</name>
		<pose>Unspecified</pose>
		<truncated>0</truncated>
		<difficult>0</difficult>
		<bndbox>
			<xmin>678</xmin>
			<ymin>298</ymin>
			<xmax>695</xmax>
			<ymax>311</ymax>
		</bndbox>
	</object>
</annotation>
